Metadata-Version: 1.0
Name: ch-my-distributions
Version: 0.1
Summary: Udacity test fot Gaussian distributions
Home-page: UNKNOWN
Author: Christos Athanasiadis
Author-email: xathanas@gmail.com
License: UNKNOWN
Platform: UNKNOWN
